m6sourceview/__init__.py
m6sourceview/__main__.py
m6sourceview/m6geo.cpython-310-x86_64-linux-gnu.so
m6sourceview/m6_library/libgeometry-shared.so
m6sourceview/m6_library/libgeometry-shared.so.6.0.0
m6sourceview/m6_library/MORET_XML_LIB/colors.xml
m6sourceview/m6_library/MORET_XML_LIB/energy_binnings.xml
m6sourceview/m6_library/MORET_XML_LIB/error_messages.xml
m6sourceview/m6_library/MORET_XML_LIB/info_messages.xml
m6sourceview/m6_library/MORET_XML_LIB/reactions.xml
m6sourceview/m6_library/MORET_XML_LIB/texts.xml
m6sourceview/m6_library/compilation_info/commit_sha
m6sourceview/m6_library/compilation_info/commit_timestamp
m6sourceview/m6_library/compilation_info/compilers-version
m6sourceview/m6_library/compilation_info/os-release
m6sourceview/m6_library/compilation_info/parallel-matrix
m6sourceview/m6_library/include/moret_bound_cond.h
m6sourceview/m6_library/include/moret_geom.h
m6sourceview.libs/libgeometry-shared-4f1a6fa3.so.6.0.0
m6sourceview-1.0.1.dist-info/METADATA
m6sourceview-1.0.1.dist-info/WHEEL
m6sourceview-1.0.1.dist-info/entry_points.txt
m6sourceview-1.0.1.dist-info/top_level.txt
m6sourceview-1.0.1.dist-info/RECORD
m6sourceview-1.0.1.dist-info/licenses/LICENSE
