Metadata-Version: 2.4
Name: m6sourceview
Version: 1.0.1
Summary: Python package for MORET6 fission source visualization in criticality mode
Author: Wilfried Monange
Requires-Python: >=3.9
License-File: LICENSE
Requires-Dist: numpy>=1.19.0
Requires-Dist: matplotlib>=3.0.0
Provides-Extra: dev
Requires-Dist: pytest; extra == "dev"
Requires-Dist: black; extra == "dev"
Requires-Dist: flake8; extra == "dev"
Dynamic: license-file
